README.md
setup.cfg
setup.py
nz/Client.py
nz/__init__.py
nz/utils/__init__.py
nz/utils/exceptions.py
nz/utils/headers.py
nz/utils/helpers.py
nz/utils/objects.py
nz_ua.py.egg-info/PKG-INFO
nz_ua.py.egg-info/SOURCES.txt
nz_ua.py.egg-info/dependency_links.txt
nz_ua.py.egg-info/requires.txt
nz_ua.py.egg-info/top_level.txt