Metadata-Version: 2.1
Name: nz-ua.py
Version: 1.1.5
Summary: Library for working with the nz-ua application.
Home-page: https://github.com/xXxCLOTIxXx/nz-ua.py
Author: Xsarz
Author-email: xsarzy@gmail.com
License: MIT
Download-URL: https://github.com/xXxCLOTIxXx/nz-ua.py/archive/refs/heads/main.zip
Keywords: nz,nz.py,nz-ua,nz-ua.py,asyncapi,python,python3,python3.x,xsarz,official
Platform: UNKNOWN
